PyAEM/__init__.py
PyAEM/bagofrequests.py
PyAEM/contentrepo.py
PyAEM/exception.py
PyAEM/handlers.py
PyAEM/httprequest.py
PyAEM/packagemanager.py
PyAEM/packagemanagerservicehtml.py
PyAEM/packagemanagerservicejson.py
PyAEM/packagemanagerservicejsp.py
PyAEM/pyaem.py
PyAEM/result.py
PyAEM/sling.py
PyAEM/test.py
PyAEM/webconsole.py
src/__init__.py
src/bagofrequests.py
src/contentrepo.py
src/exception.py
src/handlers.py
src/httprequest.py
src/packagemanager.py
src/packagemanagerservicehtml.py
src/packagemanagerservicejson.py
src/packagemanagerservicejsp.py
src/pyaem.py
src/result.py
src/sling.py
src/test.py
src/webconsole.py
pyaem3-0.0.3.dist-info/LICENSE
pyaem3-0.0.3.dist-info/METADATA
pyaem3-0.0.3.dist-info/WHEEL
pyaem3-0.0.3.dist-info/top_level.txt
pyaem3-0.0.3.dist-info/RECORD
